bittensor_drand-1.1.0.dist-info/METADATA
bittensor_drand-1.1.0.dist-info/WHEEL
bittensor_drand-1.1.0.dist-info/licenses/LICENSE
bittensor_drand/__init__.py
bittensor_drand/bittensor_drand.cpython-313-darwin.so
bittensor_drand-1.1.0.dist-info/RECORD
