Metadata-Version: 2.4
Name: bittensor-drand
Version: 1.1.0
Classifier: Development Status :: 5 - Production/Stable
Classifier: Intended Audience :: Developers
Classifier: Topic :: Software Development :: Build Tools
Classifier: License :: OSI Approved :: MIT License
Classifier: Programming Language :: Python :: 3 :: Only
Classifier: Programming Language :: Python :: 3.10
Classifier: Programming Language :: Python :: 3.11
Classifier: Programming Language :: Python :: 3.12
Classifier: Programming Language :: Python :: 3.13
Classifier: Programming Language :: Python :: 3.14
Classifier: Topic :: Scientific/Engineering
Classifier: Topic :: Scientific/Engineering :: Mathematics
Classifier: Topic :: Scientific/Engineering :: Artificial Intelligence
Classifier: Topic :: Software Development
Classifier: Topic :: Software Development :: Libraries
Classifier: Topic :: Software Development :: Libraries :: Python Modules
Requires-Dist: maturin==1.7.0 ; extra == 'dev'
Requires-Dist: pytest-asyncio==0.23.7 ; extra == 'dev'
Provides-Extra: dev
License-File: LICENSE
Summary: 
Keywords: substrate,scale,codec,bittensor,commit reveal,drand,TLE
Author-email: Roman Chkhaidze <r@latent.to>
Maintainer-email: Cortex Team <cortex@opentensor.dev>
Requires-Python: >=3.9
Project-URL: Repository, https://github.com/opentensor/bittensor-drand
